Workbook

Sheet Dashboard
A1: Painel de Saúde Financeira — Visão Mensal e Anual
A2: Atualize Entradas, Saídas e Empréstimos. Tudo aqui é dinâmico.
A4: Indicadores-chave (anual)
A5: Entradas (ano) | B5: =Entradas!N17 -> 0 | C5: Saídas (ano) | D5: =Saídas!N41 -> 0 | E5: Parcelas dívidas (ano) | F5: =Empréstimos!F18*12 -> 0 | G5: Sobra anual | H5: =Entradas!N17-Saídas!N41-Empréstimos!F18*12 -> 0
A7: Saúde Financeira — Razões e Comprometimento
A8: Taxa de poupança (sobra / entradas) | D8: =IFERROR((Entradas!N17-Saídas!N41-Empréstimos!F18*12)/Entradas!N17,0) -> 0 | E8: ≥ 20% = saudável | 10-20% = atenção | < 10% = revisar
A9: % comprometimento com dívidas | D9: =IFERROR(Empréstimos!F18*12/Entradas!N17,0) -> 0 | E9: ≤ 30% = saudável | 30-50% = atenção | > 50% = perigo
A10: % gastos fixos sobre entradas | D10: =IFERROR(Saídas!N21/Entradas!N17,0) -> 0 | E10: ≤ 50% = saudável | 50-70% = atenção | > 70% = pesado
A11: % gastos variáveis sobre entradas | D11: =IFERROR(Saídas!N39/Entradas!N17,0) -> 0 | E11: Idealmente ≤ 30%
A12: Reserva em meses de despesa (Patrimônio / despesa mensal) | D12: =IFERROR('Projeção 5 anos'!B8/((Saídas!N41+Empréstimos!F18*12)/12),0) -> 0 | E12: Meta: 6 a 12 meses
A14: Fluxo Mensal (R$)
A15: Mês | B15: Entradas | C15: Saídas | D15: Parcelas Dívidas | E15: Sobra | F15: Acumulado | G15: % Poupança | H15: Status
A16: Jan | B16: =Entradas!B17 -> 0 | C16: =Saídas!B41 -> 0 | D16: =Empréstimos!F18 -> 0 | E16: =B16-C16-D16 -> 0 | F16: =E16 -> 0 | G16: =IFERROR(E16/B16,0) -> 0 | H16: =IF(B16=0,"-",IF(E16<0,"🔴 Déficit",IF(G16>=0.2,"🟢 Saudável","🟡 Atenção"))) -> -
A17: Fev | B17: =Entradas!C17 -> 0 | C17: =Saídas!C41 -> 0 | D17: =Empréstimos!F18 -> 0 | E17: =B17-C17-D17 -> 0 | F17: =F16+E17 -> 0 | G17: =IFERROR(E17/B17,0) -> 0 | H17: =IF(B17=0,"-",IF(E17<0,"🔴 Déficit",IF(G17>=0.2,"🟢 Saudável","🟡 Atenção"))) -> -
A18: Mar | B18: =Entradas!D17 -> 0 | C18: =Saídas!D41 -> 0 | D18: =Empréstimos!F18 -> 0 | E18: =B18-C18-D18 -> 0 | F18: =F17+E18 -> 0 | G18: =IFERROR(E18/B18,0) -> 0 | H18: =IF(B18=0,"-",IF(E18<0,"🔴 Déficit",IF(G18>=0.2,"🟢 Saudável","🟡 Atenção"))) -> -
A19: Abr | B19: =Entradas!E17 -> 0 | C19: =Saídas!E41 -> 0 | D19: =Empréstimos!F18 -> 0 | E19: =B19-C19-D19 -> 0 | F19: =F18+E19 -> 0 | G19: =IFERROR(E19/B19,0) -> 0 | H19: =IF(B19=0,"-",IF(E19<0,"🔴 Déficit",IF(G19>=0.2,"🟢 Saudável","🟡 Atenção"))) -> -
A20: Mai | B20: =Entradas!F17 -> 0 | C20: =Saídas!F41 -> 0 | D20: =Empréstimos!F18 -> 0 | E20: =B20-C20-D20 -> 0 | F20: =F19+E20 -> 0 | G20: =IFERROR(E20/B20,0) -> 0 | H20: =IF(B20=0,"-",IF(E20<0,"🔴 Déficit",IF(G20>=0.2,"🟢 Saudável","🟡 Atenção"))) -> -
A21: Jun | B21: =Entradas!G17 -> 0 | C21: =Saídas!G41 -> 0 | D21: =Empréstimos!F18 -> 0 | E21: =B21-C21-D21 -> 0 | F21: =F20+E21 -> 0 | G21: =IFERROR(E21/B21,0) -> 0 | H21: =IF(B21=0,"-",IF(E21<0,"🔴 Déficit",IF(G21>=0.2,"🟢 Saudável","🟡 Atenção"))) -> -
A22: Jul | B22: =Entradas!H17 -> 0 | C22: =Saídas!H41 -> 0 | D22: =Empréstimos!F18 -> 0 | E22: =B22-C22-D22 -> 0 | F22: =F21+E22 -> 0 | G22: =IFERROR(E22/B22,0) -> 0 | H22: =IF(B22=0,"-",IF(E22<0,"🔴 Déficit",IF(G22>=0.2,"🟢 Saudável","🟡 Atenção"))) -> -
A23: Ago | B23: =Entradas!I17 -> 0 | C23: =Saídas!I41 -> 0 | D23: =Empréstimos!F18 -> 0 | E23: =B23-C23-D23 -> 0 | F23: =F22+E23 -> 0 | G23: =IFERROR(E23/B23,0) -> 0 | H23: =IF(B23=0,"-",IF(E23<0,"🔴 Déficit",IF(G23>=0.2,"🟢 Saudável","🟡 Atenção"))) -> -
A24: Set | B24: =Entradas!J17 -> 0 | C24: =Saídas!J41 -> 0 | D24: =Empréstimos!F18 -> 0 | E24: =B24-C24-D24 -> 0 | F24: =F23+E24 -> 0 | G24: =IFERROR(E24/B24,0) -> 0 | H24: =IF(B24=0,"-",IF(E24<0,"🔴 Déficit",IF(G24>=0.2,"🟢 Saudável","🟡 Atenção"))) -> -
A25: Out | B25: =Entradas!K17 -> 0 | C25: =Saídas!K41 -> 0 | D25: =Empréstimos!F18 -> 0 | E25: =B25-C25-D25 -> 0 | F25: =F24+E25 -> 0 | G25: =IFERROR(E25/B25,0) -> 0 | H25: =IF(B25=0,"-",IF(E25<0,"🔴 Déficit",IF(G25>=0.2,"🟢 Saudável","🟡 Atenção"))) -> -
A26: Nov | B26: =Entradas!L17 -> 0 | C26: =Saídas!L41 -> 0 | D26: =Empréstimos!F18 -> 0 | E26: =B26-C26-D26 -> 0 | F26: =F25+E26 -> 0 | G26: =IFERROR(E26/B26,0) -> 0 | H26: =IF(B26=0,"-",IF(E26<0,"🔴 Déficit",IF(G26>=0.2,"🟢 Saudável","🟡 Atenção"))) -> -
A27: Dez | B27: =Entradas!M17 -> 0 | C27: =Saídas!M41 -> 0 | D27: =Empréstimos!F18 -> 0 | E27: =B27-C27-D27 -> 0 | F27: =F26+E27 -> 0 | G27: =IFERROR(E27/B27,0) -> 0 | H27: =IF(B27=0,"-",IF(E27<0,"🔴 Déficit",IF(G27>=0.2,"🟢 Saudável","🟡 Atenção"))) -> -
A28: TOTAL | B28: =SUM(B16:B27) -> 0 | C28: =SUM(C16:C27) -> 0 | D28: =SUM(D16:D27) -> 0 | E28: =SUM(E16:E27) -> 0 | F28: =F27 -> 0 | G28: =IFERROR(E28/B28,0) -> 0
A73: Insights Automáticos
A74: =IF(Entradas!N17=0,"Comece preenchendo a aba Entradas.",IF((Entradas!N17-Saídas!N41-Empréstimos!F18*12)<0,"⚠ Você está gastando mais do que ganha. Revise as despesas variáveis prioritariamente.","✓ Você fechou o ano no positivo. Continue assim.")) -> Comece preenchendo a aba Entradas.
A75: =IF(Empréstimos!F18=0,"Sem dívidas cadastradas.",IF(Empréstimos!F18*12/Entradas!N17>0.3,"⚠ Comprometimento com dívidas acima de 30%. Avalie quitar a dívida com maior juros primeiro.","✓ Endividamento sob controle.")) -> Sem dívidas cadastradas.
A76: =IF(Saídas!N21/MAX(Entradas!N17,1)>0.6,"⚠ Gastos fixos consumindo mais de 60% da renda. Reduza recorrências antes de cortar variáveis.","✓ Estrutura de custos fixos enxuta.") -> ✓ Estrutura de custos fixos enxuta.
A77: =IF((Entradas!N17-Saídas!N41-Empréstimos!F18*12)/MAX(Entradas!N17,1)>=0.2,"✓ Taxa de poupança ≥ 20%: você está construindo patrimônio.","→ Mire em poupar pelo menos 20% da renda. Cada 1% extra ao mês compõe MUITO em 5 anos.") -> → Mire em poupar pelo menos 20% da renda. Cada 1% extra ao mês compõe MUITO em 5 anos.
A78: ="Patrimônio projetado em 5 anos: " & TEXT('Projeção 5 anos'!G15,"R$ #,##0") -> Patrimônio projetado em 5 anos: R$ 0

Sheet Entradas
A1: Entradas Mensais (R$) — Edite as células azuis
A3: Ano: | B3: 2026
A5: Categoria | B5: Jan | C5: Fev | D5: Mar | E5: Abr | F5: Mai | G5: Jun | H5: Jul | I5: Ago | J5: Set | K5: Out | L5: Nov | M5: Dez | N5: Total Ano
A6: Salário CLT | B6: 0 | C6: 0 | D6: 0 | E6: 0 | F6: 0 | G6: 0 | H6: 0 | I6: 0 | J6: 0 | K6: 0 | L6: 0 | M6: 0 | N6: =SUM(B6:M6) -> 0
A7: Pró-labore | B7: 0 | C7: 0 | D7: 0 | E7: 0 | F7: 0 | G7: 0 | H7: 0 | I7: 0 | J7: 0 | K7: 0 | L7: 0 | M7: 0 | N7: =SUM(B7:M7) -> 0
A8: Freelance / PJ | B8: 0 | C8: 0 | D8: 0 | E8: 0 | F8: 0 | G8: 0 | H8: 0 | I8: 0 | J8: 0 | K8: 0 | L8: 0 | M8: 0 | N8: =SUM(B8:M8) -> 0
A9: Aluguel recebido | B9: 0 | C9: 0 | D9: 0 | E9: 0 | F9: 0 | G9: 0 | H9: 0 | I9: 0 | J9: 0 | K9: 0 | L9: 0 | M9: 0 | N9: =SUM(B9:M9) -> 0
A10: Dividendos / JCP | B10: 0 | C10: 0 | D10: 0 | E10: 0 | F10: 0 | G10: 0 | H10: 0 | I10: 0 | J10: 0 | K10: 0 | L10: 0 | M10: 0 | N10: =SUM(B10:M10) -> 0
A11: Rendimentos RF | B11: 0 | C11: 0 | D11: 0 | E11: 0 | F11: 0 | G11: 0 | H11: 0 | I11: 0 | J11: 0 | K11: 0 | L11: 0 | M11: 0 | N11: =SUM(B11:M11) -> 0
A12: 13º Salário | B12: 0 | C12: 0 | D12: 0 | E12: 0 | F12: 0 | G12: 0 | H12: 0 | I12: 0 | J12: 0 | K12: 0 | L12: 0 | M12: 0 | N12: =SUM(B12:M12) -> 0
A13: Férias | B13: 0 | C13: 0 | D13: 0 | E13: 0 | F13: 0 | G13: 0 | H13: 0 | I13: 0 | J13: 0 | K13: 0 | L13: 0 | M13: 0 | N13: =SUM(B13:M13) -> 0
A14: Bônus / PLR | B14: 0 | C14: 0 | D14: 0 | E14: 0 | F14: 0 | G14: 0 | H14: 0 | I14: 0 | J14: 0 | K14: 0 | L14: 0 | M14: 0 | N14: =SUM(B14:M14) -> 0
A15: Restituição IR | B15: 0 | C15: 0 | D15: 0 | E15: 0 | F15: 0 | G15: 0 | H15: 0 | I15: 0 | J15: 0 | K15: 0 | L15: 0 | M15: 0 | N15: =SUM(B15:M15) -> 0
A16: Outros | B16: 0 | C16: 0 | D16: 0 | E16: 0 | F16: 0 | G16: 0 | H16: 0 | I16: 0 | J16: 0 | K16: 0 | L16: 0 | M16: 0 | N16: =SUM(B16:M16) -> 0
A17: TOTAL ENTRADAS | B17: =SUM(B6:B16) -> 0 | C17: =SUM(C6:C16) -> 0 | D17: =SUM(D6:D16) -> 0 | E17: =SUM(E6:E16) -> 0 | F17: =SUM(F6:F16) -> 0 | G17: =SUM(G6:G16) -> 0 | H17: =SUM(H6:H16) -> 0 | I17: =SUM(I6:I16) -> 0 | ... M17: =SUM(M6:M16) -> 0 | N17: =SUM(B17:M17) -> 0
A18: Média mensal | N18: =N17/12 -> 0

Sheet Saídas
A1: Saídas Mensais (R$) — Despesas Fixas e Variáveis
A3: Ano: | B3: =Entradas!B3 -> 2026
A5: DESPESAS FIXAS
A6: Categoria | B6: Jan | C6: Fev | D6: Mar | E6: Abr | F6: Mai | G6: Jun | H6: Jul | I6: Ago | J6: Set | K6: Out | L6: Nov | M6: Dez | N6: Total Ano
A7: Aluguel / Financiamento | B7: 0 | C7: 0 | D7: 0 | E7: 0 | F7: 0 | G7: 0 | H7: 0 | I7: 0 | J7: 0 | K7: 0 | L7: 0 | M7: 0 | N7: =SUM(B7:M7) -> 0
A8: Condomínio | B8: 0 | C8: 0 | D8: 0 | E8: 0 | F8: 0 | G8: 0 | H8: 0 | I8: 0 | J8: 0 | K8: 0 | L8: 0 | M8: 0 | N8: =SUM(B8:M8) -> 0
A9: IPTU | B9: 0 | C9: 0 | D9: 0 | E9: 0 | F9: 0 | G9: 0 | H9: 0 | I9: 0 | J9: 0 | K9: 0 | L9: 0 | M9: 0 | N9: =SUM(B9:M9) -> 0
A10: Energia | B10: 0 | C10: 0 | D10: 0 | E10: 0 | F10: 0 | G10: 0 | H10: 0 | I10: 0 | J10: 0 | K10: 0 | L10: 0 | M10: 0 | N10: =SUM(B10:M10) -> 0
A11: Água | B11: 0 | C11: 0 | D11: 0 | E11: 0 | F11: 0 | G11: 0 | H11: 0 | I11: 0 | J11: 0 | K11: 0 | L11: 0 | M11: 0 | N11: =SUM(B11:M11) -> 0
A12: Internet | B12: 0 | C12: 0 | D12: 0 | E12: 0 | F12: 0 | G12: 0 | H12: 0 | I12: 0 | J12: 0 | K12: 0 | L12: 0 | M12: 0 | N12: =SUM(B12:M12) -> 0
A13: Telefone / Celular | B13: 0 | C13: 0 | D13: 0 | E13: 0 | F13: 0 | G13: 0 | H13: 0 | I13: 0 | J13: 0 | K13: 0 | L13: 0 | M13: 0 | N13: =SUM(B13:M13) -> 0
A14: Plano de Saúde | B14: 0 | C14: 0 | D14: 0 | E14: 0 | F14: 0 | G14: 0 | H14: 0 | I14: 0 | J14: 0 | K14: 0 | L14: 0 | M14: 0 | N14: =SUM(B14:M14) -> 0
A15: Academia | B15: 0 | C15: 0 | D15: 0 | E15: 0 | F15: 0 | G15: 0 | H15: 0 | I15: 0 | J15: 0 | K15: 0 | L15: 0 | M15: 0 | N15: =SUM(B15:M15) -> 0
A16: Streaming (Netflix etc.) | B16: 0 | C16: 0 | D16: 0 | E16: 0 | F16: 0 | G16: 0 | H16: 0 | I16: 0 | J16: 0 | K16: 0 | L16: 0 | M16: 0 | N16: =SUM(B16:M16) -> 0
A17: Escola / Faculdade | B17: 0 | C17: 0 | D17: 0 | E17: 0 | F17: 0 | G17: 0 | H17: 0 | I17: 0 | J17: 0 | K17: 0 | L17: 0 | M17: 0 | N17: =SUM(B17:M17) -> 0
A18: Seguro Carro | B18: 0 | C18: 0 | D18: 0 | E18: 0 | F18: 0 | G18: 0 | H18: 0 | I18: 0 | J18: 0 | K18: 0 | L18: 0 | M18: 0 | N18: =SUM(B18:M18) -> 0
... A20: Mensalidades | B20: 0 | C20: 0 | D20: 0 | E20: 0 | F20: 0 | G20: 0 | H20: 0 | I20: 0 | J20: 0 | K20: 0 | L20: 0 | M20: 0 | N20: =SUM(B20:M20) -> 0
A21: Subtotal Fixas | B21: =SUM(B7:B20) -> 0 | C21: =SUM(C7:C20) -> 0 | D21: =SUM(D7:D20) -> 0 | E21: =SUM(E7:E20) -> 0 | F21: =SUM(F7:F20) -> 0 | G21: =SUM(G7:G20) -> 0 | H21: =SUM(H7:H20) -> 0 | I21: =SUM(I7:I20) -> 0 | ... M21: =SUM(M7:M20) -> 0 | N21: =SUM(B21:M21) -> 0
A23: DESPESAS VARIÁVEIS
A24: Categoria | B24: Jan | C24: Fev | D24: Mar | E24: Abr | F24: Mai | G24: Jun | H24: Jul | I24: Ago | J24: Set | K24: Out | L24: Nov | M24: Dez | N24: Total Ano
A25: Supermercado | B25: 0 | C25: 0 | D25: 0 | E25: 0 | F25: 0 | G25: 0 | H25: 0 | I25: 0 | J25: 0 | K25: 0 | L25: 0 | M25: 0 | N25: =SUM(B25:M25) -> 0
A26: Restaurantes / Delivery | B26: 0 | C26: 0 | D26: 0 | E26: 0 | F26: 0 | G26: 0 | H26: 0 | I26: 0 | J26: 0 | K26: 0 | L26: 0 | M26: 0 | N26: =SUM(B26:M26) -> 0
A27: Transporte / Combustível | B27: 0 | C27: 0 | D27: 0 | E27: 0 | F27: 0 | G27: 0 | H27: 0 | I27: 0 | J27: 0 | K27: 0 | L27: 0 | M27: 0 | N27: =SUM(B27:M27) -> 0
A28: Uber / 99 | B28: 0 | C28: 0 | D28: 0 | E28: 0 | F28: 0 | G28: 0 | H28: 0 | I28: 0 | J28: 0 | K28: 0 | L28: 0 | M28: 0 | N28: =SUM(B28:M28) -> 0
A29: Lazer / Cinema | B29: 0 | C29: 0 | D29: 0 | E29: 0 | F29: 0 | G29: 0 | H29: 0 | I29: 0 | J29: 0 | K29: 0 | L29: 0 | M29: 0 | N29: =SUM(B29:M29) -> 0
A30: Viagens | B30: 0 | C30: 0 | D30: 0 | E30: 0 | F30: 0 | G30: 0 | H30: 0 | I30: 0 | J30: 0 | K30: 0 | L30: 0 | M30: 0 | N30: =SUM(B30:M30) -> 0
A31: Roupas / Vestuário | B31: 0 | C31: 0 | D31: 0 | E31: 0 | F31: 0 | G31: 0 | H31: 0 | I31: 0 | J31: 0 | K31: 0 | L31: 0 | M31: 0 | N31: =SUM(B31:M31) -> 0
A32: Farmácia / Saúde | B32: 0 | C32: 0 | D32: 0 | E32: 0 | F32: 0 | G32: 0 | H32: 0 | I32: 0 | J32: 0 | K32: 0 | L32: 0 | M32: 0 | N32: =SUM(B32:M32) -> 0
A33: Presentes | B33: 0 | C33: 0 | D33: 0 | E33: 0 | F33: 0 | G33: 0 | H33: 0 | I33: 0 | J33: 0 | K33: 0 | L33: 0 | M33: 0 | N33: =SUM(B33:M33) -> 0
A34: Pets | B34: 0 | C34: 0 | D34: 0 | E34: 0 | F34: 0 | G34: 0 | H34: 0 | I34: 0 | J34: 0 | K34: 0 | L34: 0 | M34: 0 | N34: =SUM(B34:M34) -> 0
A35: Educação / Cursos | B35: 0 | C35: 0 | D35: 0 | E35: 0 | F35: 0 | G35: 0 | H35: 0 | I35: 0 | J35: 0 | K35: 0 | L35: 0 | M35: 0 | N35: =SUM(B35:M35) -> 0
A36: Reparos / Manutenção | B36: 0 | C36: 0 | D36: 0 | E36: 0 | F36: 0 | G36: 0 | H36: 0 | I36: 0 | J36: 0 | K36: 0 | L36: 0 | M36: 0 | N36: =SUM(B36:M36) -> 0
... A38: Imprevistos | B38: 0 | C38: 0 | D38: 0 | E38: 0 | F38: 0 | G38: 0 | H38: 0 | I38: 0 | J38: 0 | K38: 0 | L38: 0 | M38: 0 | N38: =SUM(B38:M38) -> 0
A39: Subtotal Variáveis | B39: =SUM(B25:B38) -> 0 | C39: =SUM(C25:C38) -> 0 | D39: =SUM(D25:D38) -> 0 | E39: =SUM(E25:E38) -> 0 | F39: =SUM(F25:F38) -> 0 | G39: =SUM(G25:G38) -> 0 | H39: =SUM(H25:H38) -> 0 | I39: =SUM(I25:I38) -> 0 | ... M39: =SUM(M25:M38) -> 0 | N39: =SUM(B39:M39) -> 0
A41: TOTAL SAÍDAS | B41: =B21+B39 -> 0 | C41: =C21+C39 -> 0 | D41: =D21+D39 -> 0 | E41: =E21+E39 -> 0 | F41: =F21+F39 -> 0 | G41: =G21+G39 -> 0 | H41: =H21+H39 -> 0 | I41: =I21+I39 -> 0 | ... M41: =M21+M39 -> 0 | N41: =SUM(B41:M41) -> 0

Sheet Empréstimos
A1: Empréstimos e Financiamentos
A3: Cadastre cada dívida abaixo. As parcelas mensais serão somadas e refletidas no Dashboard e na Projeção.
A5: Descrição | B5: Tipo | C5: Valor Original (R$) | D5: Saldo Devedor Atual (R$) | E5: Taxa Juros a.m. (%) | F5: Parcela Mensal (R$) | G5: Parcelas Restantes | H5: Total a Pagar (R$) | I5: Juros a Pagar (R$)
C6: 0 | D6: 0 | E6: 0 | F6: 0 | G6: 0 | H6: =F6*G6 -> 0 | I6: =IFERROR(H6-D6,0) -> 0
C7: 0 | D7: 0 | E7: 0 | F7: 0 | G7: 0 | H7: =F7*G7 -> 0 | I7: =IFERROR(H7-D7,0) -> 0
C8: 0 | D8: 0 | E8: 0 | F8: 0 | G8: 0 | H8: =F8*G8 -> 0 | I8: =IFERROR(H8-D8,0) -> 0
C9: 0 | D9: 0 | E9: 0 | F9: 0 | G9: 0 | H9: =F9*G9 -> 0 | I9: =IFERROR(H9-D9,0) -> 0
C10: 0 | D10: 0 | E10: 0 | F10: 0 | G10: 0 | H10: =F10*G10 -> 0 | I10: =IFERROR(H10-D10,0) -> 0
C11: 0 | D11: 0 | E11: 0 | F11: 0 | G11: 0 | H11: =F11*G11 -> 0 | I11: =IFERROR(H11-D11,0) -> 0
C12: 0 | D12: 0 | E12: 0 | F12: 0 | G12: 0 | H12: =F12*G12 -> 0 | I12: =IFERROR(H12-D12,0) -> 0
C13: 0 | D13: 0 | E13: 0 | F13: 0 | G13: 0 | H13: =F13*G13 -> 0 | I13: =IFERROR(H13-D13,0) -> 0
C14: 0 | D14: 0 | E14: 0 | F14: 0 | G14: 0 | H14: =F14*G14 -> 0 | I14: =IFERROR(H14-D14,0) -> 0
C15: 0 | D15: 0 | E15: 0 | F15: 0 | G15: 0 | H15: =F15*G15 -> 0 | I15: =IFERROR(H15-D15,0) -> 0
C16: 0 | D16: 0 | E16: 0 | F16: 0 | G16: 0 | H16: =F16*G16 -> 0 | I16: =IFERROR(H16-D16,0) -> 0
C17: 0 | D17: 0 | E17: 0 | F17: 0 | G17: 0 | H17: =F17*G17 -> 0 | I17: =IFERROR(H17-D17,0) -> 0
A18: TOTAIS | C18: =SUM(C6:C17) -> 0 | D18: =SUM(D6:D17) -> 0 | F18: =SUM(F6:F17) -> 0 | H18: =SUM(H6:H17) -> 0 | I18: =SUM(I6:I17) -> 0
A21: Indicadores de Endividamento
A22: Parcela mensal total (todas dívidas) | F22: =F18 -> 0
A23: Saldo devedor consolidado | F23: =D18 -> 0
A24: Juros a pagar (consolidado) | F24: =I18 -> 0
A25: % do juros sobre saldo devedor | F25: =IFERROR(I18/D18,0) -> 0
A26: % comprometimento da renda mensal | F26: =IFERROR(F18/(Entradas!N17/12),0) -> 0

Sheet Projeção 5 anos
A1: Projeção de Longo Prazo — 5 anos
A3: Premissas (edite as células amarelas)
A4: Inflação anual estimada | B4: 0.045
A5: Crescimento real da renda (a.a.) | B5: 0.03
A6: Rentabilidade dos investimentos (a.a.) | B6: 0.1
A7: % poupado do superávit mensal | B7: 0.8
A8: Patrimônio inicial investido (R$) | B8: 0
A10: Ano | B10: Entradas Anuais | C10: Saídas Anuais | D10: Parcelas Dívidas | E10: Superávit / Déficit | F10: Aporte Anual | G10: Patrimônio Acumulado
A11: 2026 | B11: =Entradas!N17 -> 0 | C11: =Saídas!N41 -> 0 | D11: =Empréstimos!F18*12 -> 0 | E11: =B11-C11-D11 -> 0 | F11: =MAX(E11*$B$7,0) -> 0 | G11: =$B$8*(1+$B$6)+F11 -> 0
A12: 2027 | B12: =B11*(1+$B$4+$B$5) -> 0 | C12: =C11*(1+$B$4) -> 0 | D12: =MAX(D11-D11*0.2,0) -> 0 | E12: =B12-C12-D12 -> 0 | F12: =MAX(E12*$B$7,0) -> 0 | G12: =G11*(1+$B$6)+F12 -> 0
A13: 2028 | B13: =B12*(1+$B$4+$B$5) -> 0 | C13: =C12*(1+$B$4) -> 0 | D13: =MAX(D12-D12*0.2,0) -> 0 | E13: =B13-C13-D13 -> 0 | F13: =MAX(E13*$B$7,0) -> 0 | G13: =G12*(1+$B$6)+F13 -> 0
A14: 2029 | B14: =B13*(1+$B$4+$B$5) -> 0 | C14: =C13*(1+$B$4) -> 0 | D14: =MAX(D13-D13*0.2,0) -> 0 | E14: =B14-C14-D14 -> 0 | F14: =MAX(E14*$B$7,0) -> 0 | G14: =G13*(1+$B$6)+F14 -> 0
A15: 2030 | B15: =B14*(1+$B$4+$B$5) -> 0 | C15: =C14*(1+$B$4) -> 0 | D15: =MAX(D14-D14*0.2,0) -> 0 | E15: =B15-C15-D15 -> 0 | F15: =MAX(E15*$B$7,0) -> 0 | G15: =G14*(1+$B$6)+F15 -> 0
A16: Δ vs Ano 1 | B16: =IFERROR(B15/B11-1,0) -> 0 | C16: =IFERROR(C15/C11-1,0) -> 0 | E16: =IFERROR(E15/E11-1,0) -> 0 | G16: =IFERROR(G15/G11-1,0) -> 0

Sheet Categorias
A1: Categorias de Referência (edite livremente)
A3: Tipo Entrada | B3: Tipo Saída Fixa | C3: Tipo Saída Variável | D3: Tipo Empréstimo
A4: Salário CLT | B4: Aluguel / Financiamento | C4: Supermercado | D4: Financiamento Imóvel
A5: Pró-labore | B5: Condomínio | C5: Restaurantes / Delivery | D5: Financiamento Veículo
A6: Freelance / PJ | B6: IPTU | C6: Transporte / Combustível | D6: Empréstimo Pessoal
A7: Aluguel recebido | B7: Energia | C7: Uber / 99 | D7: Cartão de Crédito (parcelado)
A8: Dividendos / JCP | B8: Água | C8: Lazer / Cinema | D8: Cheque Especial
A9: Rendimentos RF | B9: Internet | C9: Viagens | D9: Consignado
A10: 13º Salário | B10: Telefone / Celular | C10: Roupas / Vestuário | D10: FGTS antecipado
A11: Férias | B11: Plano de Saúde | C11: Farmácia / Saúde | D11: CDC
A12: Bônus / PLR | B12: Academia | C12: Presentes
A13: Restituição IR | B13: Streaming (Netflix etc.) | C13: Pets
A14: Vendas / Outros | B14: Escola / Faculdade | C14: Educação / Cursos
B15: Seguro Carro | C15: Reparos / Manutenção
B16: Seguro Vida | C16: Impostos
B17: Mensalidades | C17: Imprevistos
